drf_crud/__init__.py
drf_crud/routers.py
drf_crud/serializers.py
drf_crud/viewsets.py
drf_crud-0.1.0.dist-info/licenses/LICENSE
drf_crud-0.1.0.dist-info/METADATA
drf_crud-0.1.0.dist-info/WHEEL
drf_crud-0.1.0.dist-info/top_level.txt
drf_crud-0.1.0.dist-info/RECORD
